{
  "parent": "minecraft:block/block",
  "ambientocclusion": true,
  "gui_light": "side",
  "textures": {
    "particle": "earth_on_minecraft:block/crystallizer_active",
    "front": "earth_on_minecraft:block/crystallizer_active",
    "back": "earth_on_minecraft:block/wet_machine_side_active",
    "left": "earth_on_minecraft:block/wet_machine_side_active",
    "right": "earth_on_minecraft:block/wet_machine_side_active",
    "top": "earth_on_minecraft:block/wet_machine_top_active",
    "bottom": "earth_on_minecraft:block/wet_machine_top_active",
    "fault": "minecraft:block/redstone_lamp_on"
  },
  "elements": [
    {
      "name": "foundation",
      "from": [
        1,
        0,
        1
      ],
      "to": [
        15,
        2,
        15
      ],
      "faces": {
        "north": {
          "uv": [
            1,
            14,
            15,
            16
          ],
          "texture": "#front"
        },
        "south": {
          "uv": [
            1,
            14,
            15,
            16
          ],
          "texture": "#back"
        },
        "west": {
          "uv": [
            1,
            14,
            15,
            16
          ],
          "texture": "#left"
        },
        "east": {
          "uv": [
            1,
            14,
            15,
            16
          ],
          "texture": "#right"
        },
        "up": {
          "uv": [
            1,
            1,
            15,
            15
          ],
          "texture": "#top"
        },
        "down": {
          "uv": [
            1,
            1,
            15,
            15
          ],
          "texture": "#bottom"
        }
      }
    },
    {
      "name": "crystal_vessel",
      "from": [
        3,
        2,
        3
      ],
      "to": [
        13,
        13,
        13
      ],
      "faces": {
        "north": {
          "uv": [
            3,
            3,
            13,
            14
          ],
          "texture": "#front"
        },
        "south": {
          "uv": [
            3,
            3,
            13,
            14
          ],
          "texture": "#back"
        },
        "west": {
          "uv": [
            3,
            3,
            13,
            14
          ],
          "texture": "#left"
        },
        "east": {
          "uv": [
            3,
            3,
            13,
            14
          ],
          "texture": "#right"
        },
        "up": {
          "uv": [
            3,
            3,
            13,
            13
          ],
          "texture": "#top"
        },
        "down": {
          "uv": [
            3,
            3,
            13,
            13
          ],
          "texture": "#bottom"
        }
      }
    },
    {
      "name": "circulation_chamber",
      "from": [
        1,
        5,
        5
      ],
      "to": [
        5,
        12,
        11
      ],
      "faces": {
        "north": {
          "uv": [
            1,
            4,
            5,
            11
          ],
          "texture": "#front"
        },
        "south": {
          "uv": [
            11,
            4,
            15,
            11
          ],
          "texture": "#back"
        },
        "west": {
          "uv": [
            5,
            4,
            11,
            11
          ],
          "texture": "#left"
        },
        "east": {
          "uv": [
            5,
            4,
            11,
            11
          ],
          "texture": "#right"
        },
        "up": {
          "uv": [
            1,
            5,
            5,
            11
          ],
          "texture": "#top"
        },
        "down": {
          "uv": [
            1,
            5,
            5,
            11
          ],
          "texture": "#bottom"
        }
      }
    },
    {
      "name": "vapor_head",
      "from": [
        5,
        11,
        5
      ],
      "to": [
        11,
        16,
        11
      ],
      "faces": {
        "north": {
          "uv": [
            5,
            0,
            11,
            5
          ],
          "texture": "#front"
        },
        "south": {
          "uv": [
            5,
            0,
            11,
            5
          ],
          "texture": "#back"
        },
        "west": {
          "uv": [
            5,
            0,
            11,
            5
          ],
          "texture": "#left"
        },
        "east": {
          "uv": [
            5,
            0,
            11,
            5
          ],
          "texture": "#right"
        },
        "up": {
          "uv": [
            5,
            5,
            11,
            11
          ],
          "texture": "#top"
        },
        "down": {
          "uv": [
            5,
            5,
            11,
            11
          ],
          "texture": "#bottom"
        }
      }
    },
    {
      "name": "product_leg",
      "from": [
        5,
        1,
        5
      ],
      "to": [
        11,
        6,
        11
      ],
      "faces": {
        "north": {
          "uv": [
            5,
            10,
            11,
            15
          ],
          "texture": "#front"
        },
        "south": {
          "uv": [
            5,
            10,
            11,
            15
          ],
          "texture": "#back"
        },
        "west": {
          "uv": [
            5,
            10,
            11,
            15
          ],
          "texture": "#left"
        },
        "east": {
          "uv": [
            5,
            10,
            11,
            15
          ],
          "texture": "#right"
        },
        "up": {
          "uv": [
            5,
            5,
            11,
            11
          ],
          "texture": "#top"
        },
        "down": {
          "uv": [
            5,
            5,
            11,
            11
          ],
          "texture": "#bottom"
        }
      }
    },
    {
      "name": "service_box",
      "from": [
        12,
        6,
        4
      ],
      "to": [
        16,
        11,
        12
      ],
      "faces": {
        "north": {
          "uv": [
            12,
            5,
            16,
            10
          ],
          "texture": "#front"
        },
        "south": {
          "uv": [
            0,
            5,
            4,
            10
          ],
          "texture": "#back"
        },
        "west": {
          "uv": [
            4,
            5,
            12,
            10
          ],
          "texture": "#left"
        },
        "east": {
          "uv": [
            4,
            5,
            12,
            10
          ],
          "texture": "#right"
        },
        "up": {
          "uv": [
            12,
            4,
            16,
            12
          ],
          "texture": "#top"
        },
        "down": {
          "uv": [
            12,
            4,
            16,
            12
          ],
          "texture": "#bottom"
        }
      }
    }
  ]
}
